.coveragerc
.editorconfig
.gitignore
.travis.yml
LICENSE
README.md
pyproject.toml
requirements.txt
requirements_dev.txt
setup.cfg
setup.py
.github/workflows/python-publish.yml
democritus_algorithms/__init__.py
democritus_algorithms/algorithms.py
democritus_algorithms/algorithms_temp_utils.py
democritus_algorithms.egg-info/PKG-INFO
democritus_algorithms.egg-info/SOURCES.txt
democritus_algorithms.egg-info/dependency_links.txt
democritus_algorithms.egg-info/requires.txt
democritus_algorithms.egg-info/top_level.txt
democritus_algorithms.egg-info/zip-safe
tests/__init__.py
tests/test_algorithms.py